getable/__init__.py
getable/models.py
getable/parser.py
getable/utils.py
getable-0.1.3.dist-info/METADATA
getable-0.1.3.dist-info/WHEEL
getable-0.1.3.dist-info/licenses/LICENSE
getable-0.1.3.dist-info/RECORD
